tn3w_utils/Comic_Sans_MS.ttf
tn3w_utils/Droid_Sans_Mono.ttf
tn3w_utils/Helvetica.ttf
tn3w_utils/__init__.py
tn3w_utils/languages.json
tn3w_utils-1.1.1.dist-info/LICENSE
tn3w_utils-1.1.1.dist-info/METADATA
tn3w_utils-1.1.1.dist-info/WHEEL
tn3w_utils-1.1.1.dist-info/top_level.txt
tn3w_utils-1.1.1.dist-info/RECORD
